software_engineer_assignment/__init__.py
software_engineer_assignment/encoder_interface.py
software_engineer_assignment/gui_alarm_module.py
software_engineer_assignment/gui_components.py
software_engineer_assignment/gui_main.py
software_engineer_assignment/main.py
software_engineer_assignment/serial_interface.py
software_engineer_assignment0_1-1.0.0.dist-info/WHEEL
software_engineer_assignment0_1-1.0.0.dist-info/METADATA
software_engineer_assignment0_1-1.0.0.dist-info/RECORD
